data_disaggregation/__init__.py
data_disaggregation/actions.py
data_disaggregation/base.py
data_disaggregation/ext.py
data_disaggregation/utils.py
data_disaggregation/vtypes.py
data_disaggregation-0.11.0.dist-info/LICENSE
data_disaggregation-0.11.0.dist-info/METADATA
data_disaggregation-0.11.0.dist-info/WHEEL
data_disaggregation-0.11.0.dist-info/top_level.txt
data_disaggregation-0.11.0.dist-info/RECORD
