Metadata-Version: 2.2
Name: data-disaggregation
Version: 0.11.0
Author: Christian Winger
License: MIT
Project-URL: Documentation, https://wingechr.github.io/data-disaggregation
Project-URL: Source, https://github.com/wingechr/data-disaggregation
Platform: any
Classifier: Programming Language :: Python :: 3
Classifier: License :: OSI Approved :: MIT License
Classifier: Operating System :: OS Independent
License-File: LICENSE
Requires-Dist: pandas
Dynamic: author
Dynamic: classifier
Dynamic: description
Dynamic: description-content-type
Dynamic: license
Dynamic: platform
Dynamic: project-url
Dynamic: requires-dist
